AUTHORS.rst
CONTRIBUTING.rst
HISTORY.rst
LICENSE
MANIFEST.in
README.rst
pyproject.toml
setup.cfg
setup.py
docs/Makefile
docs/authors.rst
docs/conf.py
docs/contributing.rst
docs/history.rst
docs/index.rst
docs/installation.rst
docs/make.bat
docs/readme.rst
docs/usage.rst
pyvcftools/__init__.py
pyvcftools/cli.py
pyvcftools/pyvcftools.py
pyvcftools.egg-info/PKG-INFO
pyvcftools.egg-info/SOURCES.txt
pyvcftools.egg-info/dependency_links.txt
pyvcftools.egg-info/entry_points.txt
pyvcftools.egg-info/not-zip-safe
pyvcftools.egg-info/requires.txt
pyvcftools.egg-info/top_level.txt
tests/__init__.py
tests/test_pyvcftools.py